meadows/__init__.py
meadows/cfmt.py
meadows/cfpt.py
meadows/jsf32.py
meadows/multiarrange.py
meadows/rng.py
meadows/io/__init__.py
meadows/io/pandas.py
meadows/io/rsatoolbox.py
meadows/plot/__init__.py
meadows/plot/multiarrange.py
tests/__init__.py
tests/cfmt_score.py
tests/cfpt_score.py
tests/io_pandas.py
tests/io_rsatoolbox.py
tests/ma_checks.py
tests/ma_replicability.py
tests/rng.py
meadows-0.0.6.dist-info/METADATA
meadows-0.0.6.dist-info/WHEEL
meadows-0.0.6.dist-info/top_level.txt
meadows-0.0.6.dist-info/RECORD
