Metadata-Version: 2.1
Name: meadows
Version: 0.0.6
Summary: Meadows Scythe: the Meadows Export & Analysis toolkit
Home-page: https://github.com/meadowsresearch/scythe
Author: Jasper van den Bosch
Author-email: jasper@meadows-research.com
License: UNKNOWN
Platform: UNKNOWN
Classifier: Programming Language :: Python
Classifier: Topic :: Internet :: WWW/HTTP
Classifier: Topic :: Internet :: WWW/HTTP :: WSGI :: Application
Classifier: Intended Audience :: Science/Research
Classifier: Programming Language :: Python :: 3.7
Classifier: Programming Language :: Python :: 3.8
Classifier: Programming Language :: Python :: 3.9
Requires-Dist: numpy
Requires-Dist: pandas
Requires-Dist: randomgen (==1.19.3)
Requires-Dist: rsatoolbox (>=0.0.4)
Requires-Dist: imageio (>=2.14.1)
